Metadata-Version: 1.1
Name: django-shop-categories
Version: 0.8.beta.3
Summary: A extendable category app using django-mptt for django-shop
Home-page: http://github.com/fivethreeo/django-shop-categories/
Author: Oyvind Saltvik
Author-email: oyvind.saltvik@gmail.com
License: UNKNOWN
Platform: UNKNOWN
Classifier: Development Status :: 4 - Beta
Classifier: Environment :: Web Environment
Classifier: Intended Audience :: Developers
Classifier: License :: OSI Approved :: BSD License
Classifier: Operating System :: OS Independent
Classifier: Programming Language :: Python
Classifier: Framework :: Django
